dashai_stable_diffusion_v1_model_package/__init__.py
dashai_stable_diffusion_v1_model_package/stable_diffusion_v1_model.py
dashai_stable_diffusion_v1_model_package-0.0.9.dist-info/METADATA
dashai_stable_diffusion_v1_model_package-0.0.9.dist-info/WHEEL
dashai_stable_diffusion_v1_model_package-0.0.9.dist-info/entry_points.txt
dashai_stable_diffusion_v1_model_package-0.0.9.dist-info/RECORD
